pypuclib.cp311-win_amd64.pyd
pypuclib-1.0.4.data/data/lib/site-packages/ICYUSB.dll
pypuclib-1.0.4.data/data/lib/site-packages/PUCLIB.dll
pypuclib-1.0.4.data/data/lib/site-packages/PUCUTIL.dll
pypuclib-1.0.4.dist-info/METADATA
pypuclib-1.0.4.dist-info/WHEEL
pypuclib-1.0.4.dist-info/top_level.txt
pypuclib-1.0.4.dist-info/RECORD
