Metadata-Version: 2.1
Name: pypuclib
Version: 1.0.4
Summary: The python package for PUCLIB to control INFINICAM
Home-page: https://www.photron.co.jp/
Author: PHOTRON LIMITED
Author-email: dev-infinicam@photron.co.jp
